copyright2/__init__.py
copyright2/app.py
copyright2/configs.py
copyright2/files.py
copyright2/filesystem.py
copyright2/git.py
copyright2/timestamps.py
copyright2-0.1.1.dist-info/LICENSE
copyright2-0.1.1.dist-info/METADATA
copyright2-0.1.1.dist-info/WHEEL
copyright2-0.1.1.dist-info/entry_points.txt
copyright2-0.1.1.dist-info/top_level.txt
copyright2-0.1.1.dist-info/RECORD
