Metadata-Version: 2.1
Name: copyright2
Version: 0.1.1
Summary: Text file copyright notice linter and updater.
Author-email: Connor Newton <connor@ifthenelse.io>
Requires-Python: <4.0,>=3.10
License-File: LICENSE
Requires-Dist: marshmallow ~=3.21.3
Requires-Dist: marshmallow-dataclass ~=8.7.0
Requires-Dist: click ~=8.1.7
Requires-Dist: pyyaml ~=6.0.1
